odoo/addons/report_qweb_operating_unit/README.rst
odoo/addons/report_qweb_operating_unit/__init__.py
odoo/addons/report_qweb_operating_unit/__manifest__.py
odoo/addons/report_qweb_operating_unit/i18n/es_MX.po
odoo/addons/report_qweb_operating_unit/i18n/report_qweb_operating_unit.pot
odoo/addons/report_qweb_operating_unit/readme/CONTRIBUTORS.rst
odoo/addons/report_qweb_operating_unit/readme/DESCRIPTION.rst
odoo/addons/report_qweb_operating_unit/static/description/icon.png
odoo/addons/report_qweb_operating_unit/static/description/index.html
odoo/addons/report_qweb_operating_unit/views/report_qweb_operating_unit.xml
odoo13_addon_report_qweb_operating_unit-13.0.1.0.1.dist-info/METADATA
odoo13_addon_report_qweb_operating_unit-13.0.1.0.1.dist-info/WHEEL
odoo13_addon_report_qweb_operating_unit-13.0.1.0.1.dist-info/top_level.txt
odoo13_addon_report_qweb_operating_unit-13.0.1.0.1.dist-info/RECORD
